exam2pptvideo/__init__.py
exam2pptvideo/_entry/__init__.py
exam2pptvideo/_entry/command.py
exam2pptvideo/_entry/validation.py
exam2pptvideo/de/__init__.py
exam2pptvideo/de/exam_video.py
exam2pptvideo/de/sentence_ppt.py
exam2pptvideo/de/soundaffects/0-50.m4a
exam2pptvideo/de/soundaffects/0-50.mp3
exam2pptvideo/de/soundaffects/100.m4a
exam2pptvideo/de/soundaffects/100.mp3
exam2pptvideo/de/soundaffects/60-90.m4a
exam2pptvideo/de/soundaffects/60-90.mp3
exam2pptvideo/de/soundaffects/analysis.m4a
exam2pptvideo/de/soundaffects/analysis.mp3
exam2pptvideo/de/soundaffects/calculate.m4a
exam2pptvideo/de/soundaffects/calculate.mp3
exam2pptvideo/de/soundaffects/correct.m4a
exam2pptvideo/de/soundaffects/correct.mp3
exam2pptvideo/de/soundaffects/cover.m4a
exam2pptvideo/de/soundaffects/cover.mp3
exam2pptvideo/de/soundaffects/ending.m4a
exam2pptvideo/de/soundaffects/ending.mp3
exam2pptvideo/de/soundaffects/question.m4a
exam2pptvideo/de/soundaffects/question.mp3
exam2pptvideo/de/soundaffects/wrong.m4a
exam2pptvideo/de/soundaffects/wrong.mp3
exam2pptvideo/de/templates/exam_german_classic.pptx
exam2pptvideo/de/vocab_phrase_ppt.py
exam2pptvideo/en/__init__.py
exam2pptvideo/en/exam_video.py
exam2pptvideo/en/sentence_ppt.py
exam2pptvideo/en/soundaffects/0-50.m4a
exam2pptvideo/en/soundaffects/0-50.mp3
exam2pptvideo/en/soundaffects/100.m4a
exam2pptvideo/en/soundaffects/100.mp3
exam2pptvideo/en/soundaffects/60-90.m4a
exam2pptvideo/en/soundaffects/60-90.mp3
exam2pptvideo/en/soundaffects/analysis.m4a
exam2pptvideo/en/soundaffects/analysis.mp3
exam2pptvideo/en/soundaffects/calculate.m4a
exam2pptvideo/en/soundaffects/calculate.mp3
exam2pptvideo/en/soundaffects/correct.m4a
exam2pptvideo/en/soundaffects/correct.mp3
exam2pptvideo/en/soundaffects/cover.m4a
exam2pptvideo/en/soundaffects/cover.mp3
exam2pptvideo/en/soundaffects/ending.m4a
exam2pptvideo/en/soundaffects/ending.mp3
exam2pptvideo/en/soundaffects/question.m4a
exam2pptvideo/en/soundaffects/question.mp3
exam2pptvideo-0.1.5.dist-info/entry_points.txt
exam2pptvideo-0.1.5.dist-info/WHEEL
exam2pptvideo-0.1.5.dist-info/METADATA
exam2pptvideo-0.1.5.dist-info/RECORD
