Metadata-Version: 2.1
Name: exam2pptvideo
Version: 0.1.5
Summary: Video generator for language exam
Home-page: https://github.com/qishe-ttt/exam2pptvideo
Keywords: ppt,language,video,exam
Author: Phoenix Grey
Author-email: phoenix.grey0108@gmail.com
Requires-Python: >=3.8,<4.0
Classifier: Programming Language :: Python :: 3
Classifier: Programming Language :: Python :: 3.8
Classifier: Programming Language :: Python :: 3.9
Requires-Dist: click (>=7.1.2,<8.0.0)
Requires-Dist: pdf2image (>=1.15.1,<2.0.0)
Requires-Dist: python-pptx (>=0.6.18,<0.7.0)
Project-URL: Documentation, https://qishe-ttt.github.io/exam2pptvideo/
Project-URL: Repository, https://github.com/qishe-ttt/exam2pptvideo
